README.rst
setup.py
bin/github-status
github_status/__init__.py
github_status/create.py
github_status/listing.py
github_status/main.py
github_status/util.py
github_status.egg-info/PKG-INFO
github_status.egg-info/SOURCES.txt
github_status.egg-info/dependency_links.txt
github_status.egg-info/not-zip-safe
github_status.egg-info/requires.txt
github_status.egg-info/top_level.txt
github_status/tests/__init__.py
github_status/tests/conftest.py
github_status/tests/test_main.py
github_status/tests/test_util.py