Metadata-Version: 1.1
Name: github-status
Version: 0.0.6
Summary: Simple updates to SHA commits with CI the status
Home-page: https://github.com/alfredodeza/github-status
Author: Alfredo Deza
Author-email: alfredo@deza.pe
License: MIT
Keywords: http api github ci jenkins status sha
Platform: UNKNOWN
Classifier: Development Status :: 4 - Beta
Classifier: Intended Audience :: Developers
Classifier: License :: OSI Approved :: MIT License
Classifier: Topic :: Software Development :: Build Tools
Classifier: Topic :: Utilities
Classifier: Operating System :: MacOS :: MacOS X
Classifier: Operating System :: POSIX
Classifier: Programming Language :: Python :: 2.7
Classifier: Programming Language :: Python :: 3.3
